pytest_quickcheck/__init__.py
pytest_quickcheck/data.py
pytest_quickcheck/generator.py
pytest_quickcheck/plugin.py
pytest_quickcheck-0.9.0.dist-info/LICENSE
pytest_quickcheck-0.9.0.dist-info/METADATA
pytest_quickcheck-0.9.0.dist-info/WHEEL
pytest_quickcheck-0.9.0.dist-info/entry_points.txt
pytest_quickcheck-0.9.0.dist-info/top_level.txt
pytest_quickcheck-0.9.0.dist-info/RECORD
