Metadata-Version: 2.1
Name: pytest-quickcheck
Version: 0.9.0
Summary: pytest plugin to generate random data inspired by QuickCheck
Home-page: https://github.com/t2y/pytest-quickcheck
Author: Tetsuya Morimoto
Author-email: tetsuya.morimoto@gmail.com
License: Apache License 2.0
Keywords: test,pytest,quickcheck
Platform: linux
Platform: osx
Platform: unix
Platform: win32
Classifier: Development Status :: 4 - Beta
Classifier: Intended Audience :: Developers
Classifier: Operating System :: MacOS :: MacOS X
Classifier: Operating System :: Microsoft :: Windows
Classifier: Operating System :: POSIX
Classifier: Programming Language :: Python
Classifier: Programming Language :: Python :: 2.7
Classifier: Programming Language :: Python :: 3
Classifier: Programming Language :: Python :: 3.7
Classifier: Programming Language :: Python :: 3.8
Classifier: Programming Language :: Python :: 3.9
Classifier: Programming Language :: Python :: 3.10
Classifier: Topic :: Utilities
Classifier: Topic :: Software Development :: Testing
Classifier: Topic :: Software Development :: Libraries
Classifier: Topic :: Software Development :: Quality Assurance
